{
  "last_updated": "2025-04-23",
  "modules": [
    {
      "name": "Infobox",
      "description": "Flexible module for creating and managing abstract informational entities.",
      "package": "elfcms/infobox",
      "repo": "https://github.com/elfcms/infobox",
      "version": "1.0.0",
      "license": "MIT",
      "author": "Maxim Klassen",
      "free": true,
      "install_via": "composer",
      "composer_package": "elfcms/infobox",
      "categories": ["Content", "Pages"]
    },
    {
      "name": "Blog",
      "description": "Module for creating a blog with comments, tags, and likes.",
      "package": "elfcms/blog",
      "repo": "https://github.com/elfcms/blog",
      "version": "1.0.0",
      "license": "MIT",
      "author": "Maxim Klassen",
      "free": true,
      "install_via": "composer",
      "composer_package": "elfcms/blog",
      "categories": ["Content", "Blog"]
    },
    {
      "name": "Gallery",
      "description": "Image gallery module suitable for artists, photographers, and media-rich websites.",
      "package": "elfcms/gallery",
      "repo": "https://github.com/elfcms/gallery",
      "version": "1.0.0",
      "license": "MIT",
      "author": "Maxim Klassen",
      "free": true,
      "install_via": "composer",
      "composer_package": "elfcms/gallery",
      "categories": ["Media", "Gallery"]
    },
    {
      "name": "Geodata",
      "description": "Module for managing a database of geographic objects and data.",
      "package": "elfcms/geodata",
      "repo": "https://github.com/elfcms/geodata",
      "version": "dev",
      "license": "MIT",
      "author": "Maxim Klassen",
      "free": true,
      "install_via": "composer",
      "composer_package": "elfcms/geodata",
      "categories": ["Geodata", "Database"]
    },
  ]
}
